{"batch":{"id":"90b30129-4f86-49cf-800e-2ee0dc06e039","size":1},"interactive":false,"languages":{"java":{"mainClass":"Main","taskClass":"Task"}},"group":"NowCoder","tests":[{"status":"AC","output":"890\n","time_taken":0.451,"stdout":"890\n","stderr":"Execution time: 6.8875e-05 seconds.\n","input":"5 5 5\n1 1 1\n2 2 2\n3 3 3\n4 4 4\n5 5 5\n"}],"memoryLimit":512,"timeLimit":2000,"name":"十字阵列","url":"https://ac.nowcoder.com/acm/contest/120455/C","testType":"single","input":{"type":"stdin"},"output":{"type":"stdout"}}